tests/__init__.py
tests/tests.py
atn-0.0.2.dist-info/LICENSE
atn-0.0.2.dist-info/METADATA
atn-0.0.2.dist-info/WHEEL
atn-0.0.2.dist-info/top_level.txt
atn-0.0.2.dist-info/RECORD
