Metadata-Version: 2.1
Name: atn
Version: 0.0.2
Summary: A/T/N staging for Alzheimer's Disease based on CSF biomarkers
Home-page: https://gitlab.com/xgrg/atn/-/archive/0.0.2/atn-0.0.2.tar.gz
Author: Greg Operto
Author-email: goperto@barcelonabeta.org
License: UNKNOWN
Platform: UNKNOWN
Classifier: Programming Language :: Python :: 3
Classifier: License :: OSI Approved :: GNU General Public License v3 (GPLv3)
Classifier: Operating System :: OS Independent
